impedancefitter/RC.py
impedancefitter/__init__.py
impedancefitter/_version.py
impedancefitter/cole_cole.py
impedancefitter/cpe.py
impedancefitter/cubic_roots.py
impedancefitter/double_shell.py
impedancefitter/double_shell_ellipsoid.py
impedancefitter/double_shell_wall.py
impedancefitter/double_shell_wall_ellipsoid.py
impedancefitter/ecis.py
impedancefitter/elements.py
impedancefitter/fitter.py
impedancefitter/fra.py
impedancefitter/loss.py
impedancefitter/particle_suspension.py
impedancefitter/plotting.py
impedancefitter/postprocess.py
impedancefitter/randles.py
impedancefitter/readin.py
impedancefitter/single_shell.py
impedancefitter/single_shell_ellipsoid.py
impedancefitter/single_shell_wall.py
impedancefitter/single_shell_wall_ellipsoid.py
impedancefitter/suspensionmodels.py
impedancefitter/utils.py
impedancefitter/variance.py
impedancefitter/devices/MokuGo.json
impedancefitter/devices/R&S.json
impedancefitter/time_domain/__init__.py
impedancefitter/time_domain/cwt_reconstruction.py
impedancefitter/time_domain/fft_reconstruction.py
impedancefitter/time_domain/signals.py
impedancefitter-2.0.12.dist-info/licenses/LICENSE
impedancefitter-2.0.12.dist-info/METADATA
impedancefitter-2.0.12.dist-info/WHEEL
impedancefitter-2.0.12.dist-info/top_level.txt
impedancefitter-2.0.12.dist-info/RECORD
