Metadata-Version: 2.4
Name: impedancefitter
Version: 2.0.12
Summary: Library for fitting impedance data to equivalent circuit models.
Author-email: Leonard Thiele <leonard.thiele@uni-rostock.de>, Julius Zimmermann <julius.zimmermann@uni-rostock.de>
License:                     GNU GENERAL PUBLIC LICENSE
Project-URL: homepage, https://impedancefitter.readthedocs.io/en/latest/
Project-URL: repository, https://github.com/j-zimmermann/impedancefitter
Classifier: Programming Language :: Python :: 3
Classifier: Programming Language :: Python :: 3.10
Classifier: Programming Language :: Python :: 3.11
Classifier: Programming Language :: Python :: 3.12
Classifier: Programming Language :: Python :: 3.13
Classifier: Programming Language :: Python :: 3.14
Classifier: License :: OSI Approved :: GNU General Public License v3 or later (GPLv3+)
Classifier: Operating System :: OS Independent
Requires-Python: >=3.10
License-File: LICENSE
Requires-Dist: pyyaml>=6.0.1
Requires-Dist: pandas[excel]>=1.0.1
Requires-Dist: openturns>=1.17
Requires-Dist: numpy>=1.24.4
Requires-Dist: lmfit==1.3.2
Requires-Dist: numdifftools>=0.9.39
Requires-Dist: corner>=2.0.1
Requires-Dist: emcee>=3.0.1
Requires-Dist: tqdm>=4.42.1
Requires-Dist: pyparsing
Requires-Dist: schemdraw>=0.19
Requires-Dist: packaging
Provides-Extra: test
Requires-Dist: pytest; extra == "test"
Requires-Dist: pytest-cov; extra == "test"
Provides-Extra: dev
Requires-Dist: ruff; extra == "dev"
Requires-Dist: pre-commit; extra == "dev"
Provides-Extra: docs
Requires-Dist: sphinx; extra == "docs"
Requires-Dist: jupyter_sphinx; extra == "docs"
Requires-Dist: sphinx-rtd-theme; extra == "docs"
Provides-Extra: all
Requires-Dist: impedancefitter[dev,docs,test]; extra == "all"
Dynamic: license-file
